unigridchain/__init__.py
unigridchain/cli.py
unigridchain/config.py
unigridchain/utils.py
unigridchain/scripts/post_setup.sh
unigridchain_cli-0.0.4.dist-info/LICENSE
unigridchain_cli-0.0.4.dist-info/METADATA
unigridchain_cli-0.0.4.dist-info/WHEEL
unigridchain_cli-0.0.4.dist-info/entry_points.txt
unigridchain_cli-0.0.4.dist-info/top_level.txt
unigridchain_cli-0.0.4.dist-info/RECORD
