Metadata-Version: 2.1
Name: unigridchain-cli
Version: 0.0.4
Summary: UNKNOWN
Home-page: https://github.com/unigrid-project/unigridchain-cli
Author: UGD Software AB
Author-email: info@unigrid.org
License: UNKNOWN
Platform: UNKNOWN
License-File: LICENSE
Requires-Dist: click
Requires-Dist: requests
Requires-Dist: rich
